raredecay/__init__.py
raredecay/config.py
raredecay/data.py
raredecay/globals_.py
raredecay/meta_config.py
raredecay/ml.py
raredecay/reweight.py
raredecay/score.py
raredecay/settings.py
raredecay/stat.py
raredecay/analysis/__init__.py
raredecay/analysis/compatibility_reweight.py
raredecay/analysis/compatibility_tools.py
raredecay/analysis/ml_analysis.py
raredecay/analysis/physical_analysis.py
raredecay/analysis/reweight.py
raredecay/analysis/statistics.py
raredecay/tools/__init__.py
raredecay/tools/data_storage.py
raredecay/tools/data_tools.py
raredecay/tools/dev_tool.py
raredecay/tools/estimator.py
raredecay/tools/metrics.py
raredecay/tools/ml_scores.py
raredecay/tools/output.py
raredecay-2.1.0.dist-info/LICENSE.md
raredecay-2.1.0.dist-info/METADATA
raredecay-2.1.0.dist-info/WHEEL
raredecay-2.1.0.dist-info/dependency_links.txt
raredecay-2.1.0.dist-info/top_level.txt
raredecay-2.1.0.dist-info/RECORD
