Metadata-Version: 2.1
Name: raredecay
Version: 2.1.0
Summary: A package for analysis of rare particle decays with machine-learning algorithms
Home-page: https://github.com/mayou36/raredecay
Author: Jonas Eschle
Author-email: mayou36@jonas.eschle.com
License: Apache-2.0 License
Keywords: particle physics,analysis,machine learning,reweight,high energy physics
Platform: UNKNOWN
Classifier: Development Status :: 4 - Beta
Classifier: Intended Audience :: Science/Research
Classifier: License :: OSI Approved :: Apache Software License
Classifier: Natural Language :: English
Classifier: Operating System :: MacOS
Classifier: Operating System :: MacOS :: MacOS X
Classifier: Operating System :: POSIX :: Linux
Classifier: Operating System :: Unix
Classifier: Programming Language :: Python :: 2.7
Classifier: Programming Language :: Python :: 3.4
Classifier: Programming Language :: Python :: 3.5
Classifier: Programming Language :: Python :: 3.6
Classifier: Programming Language :: Python :: Implementation :: CPython
Classifier: Topic :: Scientific/Engineering :: Physics
Classifier: Topic :: Scientific/Engineering :: Information Analysis
Requires-Python: >=2.7
Requires-Dist: seaborn
Requires-Dist: pandas
Requires-Dist: numpy
Requires-Dist: matplotlib
Requires-Dist: future
Requires-Dist: xgboost
Requires-Dist: rep (>0.7.0)
Requires-Dist: hep-ml (>=0.5.0)
Provides-Extra: all
Requires-Dist: root-numpy ; extra == 'all'
Requires-Dist: rootpy ; extra == 'all'
Requires-Dist: rep (>=0.6.6) ; extra == 'all'
Requires-Dist: scikit-learn (>=0.18.1) ; extra == 'all'
Requires-Dist: hep-ml (>=0.4) ; extra == 'all'
